{
    "data": [{
        "date": "25 Jun",
        "message": "ini message tanggal 25 Jun",
        "status": 0
    }, {
        "date": "12 Jun",
        "message": "ini message tanggal 12 Jun",
        "status": 0
    }, {
        "date": "11 Jun",
        "message": "ini message tanggal 11 Jun",
        "status": 1
    },{
        "date": "10 Jun",
        "message": "ini message tanggal 10 Jun",
        "status": 1
    },{
        "date": "9 Jun",
        "message": "ini message tanggal 19 Jun",
        "status": 1
    },{
        "date": "1 Jun",
        "message": "ini message tanggal 1 Jun",
        "status": 0
    },{
        "date": "19 Jun",
        "message": "ini message tanggal 19 Jun",
        "status": 0
    },{
        "date": "20 Jun",
        "message": "ini message tanggal 20 Jun",
        "status": 1
    },{
        "date": "15 Jun",
        "message": "ini message tanggal 15 Jun",
        "status": 0
    },{
        "date": "30 Jun",
        "message": "ini message tanggal 30 Jun",
        "status": 1
    }]
}
